podfile/__init__.py
podfile/__version__.py
podfile/common.py
podfile/definition.py
podfile/file.py
podfile/install.py
podfile/module.py
podfile/podfile.py
podfile/podspec.py
podfile/util.py
podfile/yaml_podfile.py
podfile/yaml_target.py
podfile-1.1.2.dist-info/LICENSE
podfile-1.1.2.dist-info/METADATA
podfile-1.1.2.dist-info/WHEEL
podfile-1.1.2.dist-info/top_level.txt
podfile-1.1.2.dist-info/RECORD
