Metadata-Version: 2.1
Name: podfile
Version: 1.1.2
Summary: 这是一个python库，可以很好的编辑Podfile文件
Home-page: https://github.com/zhtut/podfile
License: MIT
Keywords: ios,python,cocoapods,podfile
Classifier: Intended Audience :: Developers
Classifier: License :: OSI Approved :: MIT License
Classifier: Programming Language :: Python :: 3.8
Classifier: Programming Language :: Python :: 3.9
Classifier: Programming Language :: Python :: 3.10
Requires-Python: >=3.8
License-File: LICENSE
Requires-Dist: pyyaml (>=6.0)
